setup.cfg
setup.py
ballsy/__init__.py
ballsy/cli.py
ballsy/config.py
ballsy/login.py
ballsy/options.py
ballsy.egg-info/PKG-INFO
ballsy.egg-info/SOURCES.txt
ballsy.egg-info/dependency_links.txt
ballsy.egg-info/entry_points.txt
ballsy.egg-info/not-zip-safe
ballsy.egg-info/requires.txt
ballsy.egg-info/top_level.txt