Metadata-Version: 1.1
Name: ballsy
Version: 0.1.0
Summary: GitHub release signing tool
Home-page: https://github.com/satta/ballsy
Author: Sascha Steinbiss
Author-email: sascha@steinbiss.name
License: BSD
Platform: any
Classifier: Development Status :: 4 - Beta
Classifier: Environment :: Console
Classifier: Intended Audience :: Developers
Classifier: License :: OSI Approved :: BSD License
Classifier: Operating System :: POSIX
Classifier: Operating System :: MacOS
Classifier: Operating System :: Unix
Classifier: Programming Language :: Python
Classifier: Programming Language :: Python :: 2
Classifier: Programming Language :: Python :: 3
